superpower_gui/__init__.py
superpower_gui/_nbdev.py
superpower_gui/config.py
superpower_gui/controller.py
superpower_gui/items.py
superpower_gui/log.py
superpower_gui/main.py
superpower_gui/mvc.py
superpower_gui/results.py
superpower_gui/rpy.py
superpower_gui/settings.py
superpower_gui/traits.py
superpower_gui/widget_containers.py
superpower_gui/widgets.py
superpower_gui/models/__init__.py
superpower_gui/models/anova.py
superpower_gui/models/chisq.py
superpower_gui/models/corr.py
superpower_gui/models/error_bars.py
superpower_gui/models/mod.py
superpower_gui/models/moderation.py
superpower_gui/models/ratio.py
superpower_gui/models/reg.py
superpower_gui/models/slope_graph.py
superpower_gui/models/ttest.py
superpower_gui/superpower/__init__.py
superpower_gui/superpower/chisq.py
superpower_gui/superpower/corr.py
superpower_gui/superpower/correlation.py
superpower_gui/superpower/ttest.py
superpower_gui/views/__init__.py
superpower_gui/views/anova.py
superpower_gui/views/bar.py
superpower_gui/views/boxplot.py
superpower_gui/views/chisq.py
superpower_gui/views/corr.py
superpower_gui/views/error_bars.py
superpower_gui/views/line_graph.py
superpower_gui/views/mod.py
superpower_gui/views/mod_est.py
superpower_gui/views/mod_land.py
superpower_gui/views/mod_plot.py
superpower_gui/views/ratio.py
superpower_gui/views/reg.py
superpower_gui/views/slopes_graph.py
superpower_gui/views/table_widget.py
superpower_gui/views/tabs.py
superpower_gui/views/ttest.py
superpower_gui-0.3.0.dist-info/LICENSE
superpower_gui-0.3.0.dist-info/METADATA
superpower_gui-0.3.0.dist-info/WHEEL
superpower_gui-0.3.0.dist-info/entry_points.txt
superpower_gui-0.3.0.dist-info/top_level.txt
superpower_gui-0.3.0.dist-info/RECORD
