Metadata-Version: 2.1
Name: superpower-gui
Version: 0.3.0
Summary: A statistical power analysis application
Home-page: https://github.itap.purdue.edu/superpower_gui/superpower_gui/tree/master/
Author: Nicole Brewer
Author-email: brewer36@purdue.edu
License: Apache Software License 2.0
Keywords: statistics power analysis
Platform: UNKNOWN
Classifier: Development Status :: 3 - Alpha
Classifier: Intended Audience :: Developers
Classifier: License :: OSI Approved :: Apache Software License
Classifier: Natural Language :: English
Classifier: Programming Language :: Python :: 3.6
Classifier: Programming Language :: Python :: 3.7
Classifier: Programming Language :: Python :: 3.8
Requires-Python: >=3.6
Requires-Dist: matplotlib
Requires-Dist: ipympl
Requires-Dist: ipywidgets
Requires-Dist: fastcore
Requires-Dist: numpy (>=1.19)
Requires-Dist: pandas
Requires-Dist: traittypes
Requires-Dist: rpy2 (==3.4)
Requires-Dist: r-devtools
Requires-Dist: r-snowfall
Requires-Dist: r-languageserver
Requires-Dist: r-emmeans
Requires-Dist: r-lme4
Requires-Dist: r-lmerTest
Requires-Dist: r-MASS
Requires-Dist: r-tidyverse
Requires-Dist: r-afex
Requires-Dist: r-ggplot2
Requires-Dist: r-data.table
Requires-Dist: r-psych
Requires-Dist: r-plotly
Requires-Dist: r-arm
Requires-Dist: r-plyr
Requires-Dist: r-magrittr
Requires-Dist: r-knitr
Requires-Dist: r-Matrix
Requires-Dist: r-car
Requires-Dist: r-rlist
Requires-Dist: r-reshape
Requires-Dist: r-mvtnorm
Requires-Dist: r-matrixcalc
Requires-Dist: r-copula
Requires-Dist: r-VGAM
Requires-Dist: r-lavaan
